MANIFEST.in
README.rst
requirements.txt
setup.py
GenAPI.egg-info/PKG-INFO
GenAPI.egg-info/SOURCES.txt
GenAPI.egg-info/dependency_links.txt
GenAPI.egg-info/not-zip-safe
GenAPI.egg-info/requires.txt
GenAPI.egg-info/top_level.txt
docs/build/html/_sources/index.txt
genapi/__init__.py
genapi/tests/test_login.py