Metadata-Version: 1.1
Name: GenAPI
Version: 0.0.8
Summary: A Python API for the Genesis platform.
Home-page: https://github.com/genialis/genesis-genapi/
Author: Genialis d.o.o.
Author-email: dev-team@genialis.com
License: Proprietary software
Platform: UNKNOWN
Classifier: Development Status :: 4 - Beta
Classifier: Environment :: Console
Classifier: Intended Audience :: Developers
Classifier: License :: Other/Proprietary License
Classifier: Operating System :: OS Independent
Classifier: Programming Language :: Python
